[
  {
    "id": "4bda9719-1158-4919-9247-be0f3ce8dee4",
    "date": "2026-06-11",
    "category": "励志",
    "title": "今日微光",
    "content": "今天早起看了场日出，发现黑暗褪去不是一瞬间的事——是一点点亮起来的。原来坚持，就是等光慢慢来。",
    "image_url": "/images/2026-06-11-0.jpg",
    "image_author": "",
    "created_at": "2026-06-11T12:45:15.398Z"
  },
  {
    "id": "8d78c71b-334f-41c3-a231-260211af0aed",
    "date": "2026-06-11",
    "category": "励志",
    "title": "日常的微光",
    "content": "早起看到阳光洒在窗台，突然觉得，生活里的小坚持，就像这束光，慢慢会把黑暗都照亮。",
    "image_url": "/images/2026-06-11-1.jpg",
    "image_author": "",
    "created_at": "2026-06-11T12:45:17.529Z"
  },
  {
    "id": "508676f0-3832-4f6e-8760-6cf18a63e03e",
    "date": "2026-06-11",
    "category": "励志",
    "title": "日常微光",
    "content": "今天看到阳台上的绿植，冒出了新芽。原来成长不需要轰轰烈烈，只要每天多晒一点太阳。",
    "image_url": "/images/2026-06-11-2.jpg",
    "image_author": "",
    "created_at": "2026-06-11T12:45:20.043Z"
  },
  {
    "id": "5f403ce0-add9-49c0-8977-295cc2f94861",
    "date": "2026-06-11",
    "category": "励志",
    "title": "慢慢来",
    "content": "今天看到路边的小草，在石头缝里也长出来了。突然觉得，慢一点没关系，只要还在向上。你也是啊。",
    "image_url": "/images/2026-06-11-3.jpg",
    "image_author": "",
    "created_at": "2026-06-11T12:45:23.041Z"
  },
  {
    "id": "5c7804c9-c84a-40d8-9fa2-c8a455768fac",
    "date": "2026-06-11",
    "category": "情感",
    "title": "今日份的温柔",
    "content": "傍晚的风很轻，把一天的疲惫都吹散了。突然觉得，生活里的小确幸，往往就藏在这些不经意的瞬间里。",
    "image_url": "/images/2026-06-11-4.jpg",
    "image_author": "",
    "created_at": "2026-06-11T12:45:26.027Z"
  },
  {
    "id": "7f4e3cb5-91b6-411b-a8f9-3828e4d320d5",
    "date": "2026-06-11",
    "category": "情感",
    "title": "午后随想",
    "content": "晾衣服时发现阳光刚好照在床单上，那一瞬间突然觉得，生活里的小确幸，原来都藏在这些不起眼的日常里。",
    "image_url": "/images/2026-06-11-5.jpg",
    "image_author": "",
    "created_at": "2026-06-11T12:45:28.452Z"
  },
  {
    "id": "12846ffd-48d5-4ee6-ac2e-4193bf290dd6",
    "date": "2026-06-11",
    "category": "情感",
    "title": "夜晚的安宁",
    "content": "把手机调成静音，泡一杯温茶，看窗外灯光零星亮起。原来平静不是什么都拥有，而是什么都不缺。",
    "image_url": "/images/2026-06-11-6.jpg",
    "image_author": "",
    "created_at": "2026-06-11T12:45:30.760Z"
  },
  {
    "id": "b53baecf-2ea7-47dd-8b9a-ce85dfccefb4",
    "date": "2026-06-11",
    "category": "情感",
    "title": "日常碎片",
    "content": "今天路过花店，顺手买了一束雏菊。放在窗台上，阳光一照，整间屋子都亮了。原来快乐，有时候就是一朵花的距离。",
    "image_url": "/images/2026-06-11-7.jpg",
    "image_author": "",
    "created_at": "2026-06-11T12:45:32.812Z"
  },
  {
    "id": "7209944e-6ab5-452b-95ba-eb093882abf2",
    "date": "2026-06-11",
    "category": "早安",
    "title": "清晨小记",
    "content": "窗台上晾着的白衬衫被风吹得晃来晃去，刚好接住了一缕阳光。原来美好，就藏在这些不经意的瞬间里。",
    "image_url": "/images/2026-06-11-8.jpg",
    "image_author": "",
    "created_at": "2026-06-11T12:45:34.623Z"
  },
  {
    "id": "f4aad74d-afba-480f-8ebf-cce4c4a7d818",
    "date": "2026-06-11",
    "category": "早安",
    "title": "早安｜晨光与茶",
    "content": "早起泡了杯茶，看叶子慢慢舒展，像日子一点点打开。不急不躁，也挺好。",
    "image_url": "/images/2026-06-11-9.jpg",
    "image_author": "",
    "created_at": "2026-06-11T12:45:37.206Z"
  },
  {
    "id": "cec04692-e2e2-4e0b-9def-0aa36ebbf166",
    "date": "2026-06-11",
    "category": "早安",
    "title": "晨间絮语",
    "content": "早起煮了杯热茶，看窗外树叶摇晃。突然觉得，日子不就是这样嘛，简单点，慢一点，也挺好。",
    "image_url": "/images/2026-06-11-10.jpg",
    "image_author": "",
    "created_at": "2026-06-11T12:45:38.810Z"
  },
  {
    "id": "8b422bd2-0028-4f0c-8119-f7a7507c8e58",
    "date": "2026-06-11",
    "category": "早安",
    "title": "晨光絮语",
    "content": "早上煮粥时看着热气升腾，突然觉得日子就是这样，慢慢熬，总有香气。新的一天，愿你也尝到甜头。",
    "image_url": "/images/2026-06-11-11.jpg",
    "image_author": "",
    "created_at": "2026-06-11T12:45:40.605Z"
  },
  {
    "id": "6617ce65-0163-40e2-8e41-f67f0b02b40e",
    "date": "2026-06-11",
    "category": "晚安",
    "title": "今日晚安",
    "content": "路灯把影子拉得好长，走着走着，忽然觉得今天那些烦恼，其实也没那么重要了。",
    "image_url": "/images/2026-06-11-12.jpg",
    "image_author": "",
    "created_at": "2026-06-11T12:45:42.630Z"
  },
  {
    "id": "0f8e7fa5-d718-4bfb-98ce-1de9fc4821f4",
    "date": "2026-06-11",
    "category": "晚安",
    "title": "夜色安宁",
    "content": "今晚的月亮很安静，像在等谁先开口。我决定把白天没说完的话，都留到梦里再说。",
    "image_url": "/images/2026-06-11-13.jpg",
    "image_author": "",
    "created_at": "2026-06-11T12:45:44.343Z"
  },
  {
    "id": "2aef4d70-6991-4565-8074-8e12251752da",
    "date": "2026-06-11",
    "category": "晚安",
    "title": "晚安·关灯时刻",
    "content": "今天忙完所有事，关灯的那一瞬间，感觉自己像一块终于充满电的手机，可以安心休眠了。",
    "image_url": "/images/2026-06-11-14.jpg",
    "image_author": "",
    "created_at": "2026-06-11T12:45:46.504Z"
  },
  {
    "id": "90a4eaa9-3fbe-44e7-ad72-a1f18896353a",
    "date": "2026-06-11",
    "category": "晚安",
    "title": "晚安·第4条",
    "content": "把今天的烦恼叠好放进口袋，留点力气明天再丢。睡吧，梦里会有月亮替你说晚安。",
    "image_url": "/images/2026-06-11-15.jpg",
    "image_author": "",
    "created_at": "2026-06-11T12:45:48.692Z"
  },
  {
    "id": "33b9777b-4137-43a0-95e6-1ffceeef46a4",
    "date": "2026-06-11",
    "category": "日常",
    "title": "今日小确幸",
    "content": "傍晚的风刚好温柔，路边的猫刚好伸懒腰。生活里那些不经意的瞬间，比计划好的更动人。",
    "image_url": "/images/2026-06-11-16.jpg",
    "image_author": "",
    "created_at": "2026-06-11T12:45:50.751Z"
  },
  {
    "id": "6266fbe5-ae9f-4762-8828-68da4d4e3365",
    "date": "2026-06-11",
    "category": "日常",
    "title": "午后小记",
    "content": "阳光洒在地板上，猫伸了个懒腰，我的咖啡刚好不烫了。日子嘛，不就是这些刚刚好的瞬间拼成的？",
    "image_url": "/images/2026-06-11-17.jpg",
    "image_author": "",
    "created_at": "2026-06-11T12:45:53.256Z"
  },
  {
    "id": "432af5a4-7b4d-4894-a2bb-76c602932ee5",
    "date": "2026-06-11",
    "category": "日常",
    "title": "日常小记",
    "content": "傍晚的风终于有了凉意，吹得树叶沙沙响。耳机里的歌刚好播到最爱的那首，突然觉得今天也没那么糟。",
    "image_url": "/images/2026-06-11-18.jpg",
    "image_author": "",
    "created_at": "2026-06-11T12:45:55.639Z"
  },
  {
    "id": "803f1e38-b33a-456c-b0ef-0b0ef3ff2299",
    "date": "2026-06-11",
    "category": "日常",
    "title": "日常",
    "content": "傍晚的风凉凉的，路灯下影子拉得很长。耳机里刚好放到喜欢的歌，突然觉得今天也没那么糟。",
    "image_url": "/images/2026-06-11-19.jpg",
    "image_author": "",
    "created_at": "2026-06-11T12:45:57.587Z"
  },
  {
    "id": "35bd55ae-249f-4420-83b2-bd3146010f67",
    "date": "2026-06-11",
    "category": "励志",
    "title": "今日份微光",
    "content": "今天把积灰的花盆翻出来种了棵薄荷，忽然觉得，生活里的光，都是自己点亮的。",
    "image_url": "/images/2026-06-11-0.jpg",
    "image_author": "",
    "created_at": "2026-06-11T10:43:30.952Z"
  },
  {
    "id": "cfe74521-9acf-4ac2-b17a-41b7c4baf3b9",
    "date": "2026-06-11",
    "category": "励志",
    "title": "微光",
    "content": "今天早起看到窗外的晨光，突然觉得，再难的日子，也就这么一点点亮起来。你也是吧？",
    "image_url": "/images/2026-06-11-1.jpg",
    "image_author": "",
    "created_at": "2026-06-11T10:43:33.953Z"
  },
  {
    "id": "1fa6fea7-2c77-4fe1-a055-22bd8ce78410",
    "date": "2026-06-11",
    "category": "励志",
    "title": "慢慢来",
    "content": "今天看到阳台上晒的被子，突然觉得生活就是这样，不急不躁，该暖的时候自然会暖。",
    "image_url": "/images/2026-06-11-2.jpg",
    "image_author": "",
    "created_at": "2026-06-11T10:43:36.477Z"
  },
  {
    "id": "06d6aa00-d7e8-464e-bfe0-0febcf8b5c98",
    "date": "2026-06-11",
    "category": "励志",
    "title": "坚持的力量",
    "content": "今天跑了五公里，最后两公里全靠那句“再坚持一下”。原来极限之后，真的还有路。",
    "image_url": "/images/2026-06-11-3.jpg",
    "image_author": "",
    "created_at": "2026-06-11T10:43:39.175Z"
  },
  {
    "id": "138cd8cf-1323-4837-95ac-361c3cf8cf2b",
    "date": "2026-06-11",
    "category": "情感",
    "title": "今日份温柔",
    "content": "傍晚的风有点凉，路灯把影子拉得很长。突然觉得，一个人走回家的路，也挺安静的。",
    "image_url": "/images/2026-06-11-4.jpg",
    "image_author": "",
    "created_at": "2026-06-11T10:43:41.487Z"
  },
  {
    "id": "d60698cc-9770-48ef-99d0-b1440d375580",
    "date": "2026-06-11",
    "category": "情感",
    "title": "今晚的月光",
    "content": "今晚的月光很亮，却没人在身边分享。我拍了张照片发给自己，原来有些美好，注定要独自收藏。",
    "image_url": "/images/2026-06-11-5.jpg",
    "image_author": "",
    "created_at": "2026-06-11T10:43:44.410Z"
  },
  {
    "id": "37191c5e-367e-4023-8919-de5264bdb10e",
    "date": "2026-06-11",
    "category": "情感",
    "title": "安静的陪伴",
    "content": "傍晚的风很轻，路边的小猫在打盹，我忽然觉得，日子不需要太热闹，这样安静地待着就很好。",
    "image_url": "/images/2026-06-11-6.jpg",
    "image_author": "",
    "created_at": "2026-06-11T10:43:48.632Z"
  },
  {
    "id": "37e11080-5b36-4232-b82b-3a3a02002403",
    "date": "2026-06-11",
    "category": "情感",
    "title": "生活的褶皱",
    "content": "晾衣服的时候，发现阳光把衬衫晒出了风的味道。突然觉得日子真好，连等待都变得柔软。",
    "image_url": "/images/2026-06-11-7.jpg",
    "image_author": "",
    "created_at": "2026-06-11T10:43:51.133Z"
  },
  {
    "id": "ac3dd6cf-65af-4d7b-b998-c76efd9f4a3c",
    "date": "2026-06-11",
    "category": "早安",
    "title": "晨光集",
    "content": "窗台上的绿植沾着露水，像刚醒的孩子揉眼睛。今天也想慢慢过，不赶时间，只赶温柔。",
    "image_url": "/images/2026-06-11-8.jpg",
    "image_author": "",
    "created_at": "2026-06-11T10:43:54.097Z"
  },
  {
    "id": "4868c1a7-7782-4427-a505-6f06db129a53",
    "date": "2026-06-11",
    "category": "早安",
    "title": "早安·日常",
    "content": "早起煮了杯咖啡，窗外的光正好洒在杯沿上。生活嘛，就是这些微小的温柔时刻。愿你今天也能遇见这样的瞬间。",
    "image_url": "/images/2026-06-11-9.jpg",
    "image_author": "",
    "created_at": "2026-06-11T10:43:56.535Z"
  },
  {
    "id": "9d826e3d-471b-4540-8548-6041128878db",
    "date": "2026-06-11",
    "category": "早安",
    "title": "早晨的仪式感",
    "content": "煮一杯热茶，看窗外阳光慢慢爬上来。日子不需要太赶，慢一点，反而能装下更多喜欢。新的一天，愿你也如此。🌤️",
    "image_url": "/images/2026-06-11-10.jpg",
    "image_author": "",
    "created_at": "2026-06-11T10:43:59.596Z"
  },
  {
    "id": "f4e26a34-f009-4f1c-bb4c-ec5a770d5063",
    "date": "2026-06-11",
    "category": "早安",
    "title": "阳光正好",
    "content": "早上的阳光洒进厨房，煮咖啡时闻到豆香，心情一下子亮了。新的一天，从对自己好一点开始。",
    "image_url": "/images/2026-06-11-11.jpg",
    "image_author": "",
    "created_at": "2026-06-11T10:44:02.028Z"
  },
  {
    "id": "75f25c11-32f5-4b9c-aca9-b72ec5859f07",
    "date": "2026-06-11",
    "category": "晚安",
    "title": "今日晚安",
    "content": "夜风把窗帘吹得轻轻鼓起来，像在说今天辛苦了。其实也没做什么大事，但能安稳度过一天，就很好了。",
    "image_url": "/images/2026-06-11-12.jpg",
    "image_author": "",
    "created_at": "2026-06-11T10:44:05.418Z"
  },
  {
    "id": "b43e83da-c1ab-4ab4-8cb0-4e3b138d3e1b",
    "date": "2026-06-11",
    "category": "晚安",
    "title": "今日晚安",
    "content": "今晚的月亮很圆，风也温柔。忽然觉得，生活里的小确幸，原来一直都在。",
    "image_url": "/images/2026-06-11-13.jpg",
    "image_author": "",
    "created_at": "2026-06-11T10:44:07.953Z"
  },
  {
    "id": "8e20ecf4-8607-4f2e-a12d-585371492814",
    "date": "2026-06-11",
    "category": "晚安",
    "title": "晚安·今日份",
    "content": "今天认真煮了一碗面，加了溏心蛋和青菜，汤也喝光了。生活的小治愈，往往就藏在好好吃饭这件事里。",
    "image_url": "/images/2026-06-11-14.jpg",
    "image_author": "",
    "created_at": "2026-06-11T10:44:10.228Z"
  },
  {
    "id": "e4d73940-86d1-4b61-8a6d-5a5e91cb9003",
    "date": "2026-06-11",
    "category": "晚安",
    "title": "夜晚的平静",
    "content": "今晚的月亮很圆，像老朋友的笑脸。我站在窗边发呆，觉得一天里最安静的时刻，就是现在。你睡了吗？",
    "image_url": "/images/2026-06-11-15.jpg",
    "image_author": "",
    "created_at": "2026-06-11T10:44:13.109Z"
  },
  {
    "id": "9242d753-09e6-481b-94bd-09a287eb4558",
    "date": "2026-06-11",
    "category": "日常",
    "title": "今日份的小确幸",
    "content": "傍晚的风凉凉的，吹得树叶沙沙响。路边卖糖炒栗子的香味飘过来，忽然觉得，生活就这样慢慢过着也挺好。",
    "image_url": "/images/2026-06-11-16.jpg",
    "image_author": "",
    "created_at": "2026-06-11T10:44:16.002Z"
  },
  {
    "id": "cd991bae-7da0-4571-a16f-28566be79176",
    "date": "2026-06-11",
    "category": "日常",
    "title": "午后小记",
    "content": "阳光把影子拉得老长，猫在窗台上打盹儿。这样的午后，连时间都走得慢了些。",
    "image_url": "/images/2026-06-11-17.jpg",
    "image_author": "",
    "created_at": "2026-06-11T10:44:19.493Z"
  },
  {
    "id": "f73f600a-edbb-4e1e-9dcc-e89d39163074",
    "date": "2026-06-11",
    "category": "日常",
    "title": "生活碎片",
    "content": "傍晚的风很温柔，夕阳把影子拉得好长。突然觉得，平凡日子里的小确幸，才是最让人安心的。你也有这样的瞬间吗？",
    "image_url": "/images/2026-06-11-18.jpg",
    "image_author": "",
    "created_at": "2026-06-11T10:44:22.058Z"
  },
  {
    "id": "eb8d7734-2629-4294-897f-0d77123b4d9e",
    "date": "2026-06-11",
    "category": "日常",
    "title": "日常·小确幸",
    "content": "阳光透过树叶洒在脸上，风把心事吹散了一半。剩下的那一半，就留给今晚的月亮吧。",
    "image_url": "/images/2026-06-11-19.jpg",
    "image_author": "",
    "created_at": "2026-06-11T10:44:24.495Z"
  }
]